forumsentry/__init__.py
forumsentry/api.py
forumsentry/config.py
forumsentry/configuration_import_api.py
forumsentry/documents_api.py
forumsentry/errors.py
forumsentry/http_listener_policy_api.py
forumsentry/http_remote_policy_api.py
forumsentry/json_policies_api.py
forumsentry/key_pairs_api.py
forumsentry/serialization.py
forumsentry/ssl_initiation_policy_api.py
forumsentry/ssl_termination_policy_api.py
forumsentry/task_list_groups_api.py
forumsentry/task_lists_api.py
forumsentry-0.17.156.dist-info/DESCRIPTION.rst
forumsentry-0.17.156.dist-info/METADATA
forumsentry-0.17.156.dist-info/RECORD
forumsentry-0.17.156.dist-info/WHEEL
forumsentry-0.17.156.dist-info/metadata.json
forumsentry-0.17.156.dist-info/top_level.txt
forumsentry_api/__init__.py
forumsentry_api/models/__init__.py
forumsentry_api/models/document.py
forumsentry_api/models/html_policies.py
forumsentry_api/models/html_policy.py
forumsentry_api/models/http_listener_policy.py
forumsentry_api/models/http_remote_policy.py
forumsentry_api/models/json_policies.py
forumsentry_api/models/ssl_initiation_policy.py
forumsentry_api/models/ssl_termination_policy.py
forumsentry_api/models/task_list.py
forumsentry_api/models/task_list_group.py
forumsentry_api/models/virtual_directory.py
