Metadata-Version: 2.0
Name: forumsentry
Version: 0.17.156
Summary: Forum Sentry sdk for Python
Home-page: https://github.com/awalker125/forumsentry-sdk-for-python
Author: awalker125
Author-email: awalker125@users.noreply.github.com
License: MIT
Keywords: forumsentry automation api sdk
Platform: UNKNOWN
Classifier: Development Status :: 2 - Pre-Alpha
Classifier: Intended Audience :: Developers
Classifier: Intended Audience :: System Administrators
Classifier: License :: OSI Approved :: MIT License
Classifier: Operating System :: OS Independent
Classifier: Topic :: Software Development :: Build Tools
Classifier: Topic :: Software Development :: Libraries :: Python Modules
Classifier: Topic :: Utilities
Classifier: Programming Language :: Python :: 2.7
Requires-Python: >=2.7
Requires-Dist: futures
Requires-Dist: requests
Requires-Dist: urllib3
Requires-Dist: jmespath
